CHANGELOG.md
bootloader/__init__.py
bootloader/ue/__init__.py
bootloader/ue/cli/__init__.py
bootloader/ue/cli/uassetdump.py
bootloader/ue/constant/__init__.py
bootloader/ue/constant/uasset.py
bootloader/ue/model/__init__.py
bootloader/ue/model/uasset.py
bootloader/ue/utils/__init__.py
bootloader/ue/utils/uasset_dump.py
uasset_dump-0.0.17.dist-info/LICENSE.md
uasset_dump-0.0.17.dist-info/WHEEL
uasset_dump-0.0.17.dist-info/entry_points.txt
uasset_dump-0.0.17.dist-info/METADATA
uasset_dump-0.0.17.dist-info/RECORD
