Metadata-Version: 2.1
Name: uasset-dump
Version: 0.0.17
Summary: Command-line Interface (CLI) responsible for returning the list of the assets of an Unreal Engine project into a JSON structure
Home-page: https://github.com/bootloader-studio/cli-uasset-dump
License: SEE LICENSE IN <LICENSE.md>
Keywords: cli,tool,utility,unreal,engine,asset,inventory,dump,json
Author: Daniel CAUNE
Author-email: daniel@bootloader.studio
Requires-Python: >=3.9,<4.0
Classifier: Development Status :: 5 - Production/Stable
Classifier: License :: Other/Proprietary License
Classifier: Operating System :: OS Independent
Classifier: Programming Language :: Python
Classifier: Programming Language :: Python :: 3
Classifier: Programming Language :: Python :: 3.9
Classifier: Programming Language :: Python :: 3.10
Classifier: Programming Language :: Python :: 3.11
Classifier: Topic :: Software Development :: Libraries
Requires-Dist: perseus-core-library (>=1.19.3,<2.0.0)
Project-URL: Repository, https://github.com/bootloader-studio/cli-uasset-dump
